empty_zones/empty_zones/empty_zones.py
empty_zones/empty_zones/empty_zones.rego
empty_zones/empty_zones/manifest.toml
empty_zones/empty_zones/test_empty_zones.py
opsbox_r53_checks-0.2.0.dist-info/LICENCE.txt
opsbox_r53_checks-0.2.0.dist-info/METADATA
opsbox_r53_checks-0.2.0.dist-info/WHEEL
opsbox_r53_checks-0.2.0.dist-info/entry_points.txt
opsbox_r53_checks-0.2.0.dist-info/top_level.txt
opsbox_r53_checks-0.2.0.dist-info/RECORD
