Metadata-Version: 2.2
Name: opsbox-r53-checks
Version: 0.2.0
Summary: Collection of Route 53 checks for opsbox
Requires-Python: ==3.11.*
License-File: LICENCE.txt
Requires-Dist: opsbox-r53-provider>=0.1.3
Requires-Dist: opsbox-rego-handler>=0.2.0
